{
  "_fv": 57,
  "_type": "recipe",
  "definition": {
    "recipeType": "Crafting",
    "recipeRetstackSize": 8,
    "group": "",
    "cookingBookCategory": "MISC",
    "xpReward": 0.0,
    "cookingTime": 200,
    "craftingBookCategory": "MISC",
    "recipeShapeless": true,
    "recipeSlots": [
      {
        "value": "TAG:minecraft:music_discs"
      },
      {
        "value": ""
      },
      {
        "value": ""
      },
      {
        "value": ""
      },
      {
        "value": ""
      },
      {
        "value": ""
      },
      {
        "value": ""
      },
      {
        "value": ""
      },
      {
        "value": ""
      }
    ],
    "recipeReturnStack": {
      "value": "CUSTOM:RecordFragment"
    },
    "name": "record_fragment_recipe",
    "namespace": "mod"
  }
}